Serializer/JsonDeserializer.py
Serializer/JsonParser.py
Serializer/JsonSerializer.py
Serializer/SerializerFactory.py
Serializer/XmlDeserializer.py
Serializer/XmlParser.py
Serializer/XmlSerializer.py
Serializer/__init__.py
Serializer/constants.py
CactusSerializer-3.0.0.dist-info/METADATA
CactusSerializer-3.0.0.dist-info/WHEEL
CactusSerializer-3.0.0.dist-info/top_level.txt
CactusSerializer-3.0.0.dist-info/RECORD
