Metadata-Version: 2.1
Name: CactusSerializer
Version: 3.0.0
Summary: module for serialization/deserialization(JSON, XML)
Home-page: https://github.com/Antilevskaya-Ksenia-153501/Python-labs/tree/lab3
Author: Ksenia Antilevskaya
Author-email: antikevkun@gmail.com
Classifier: Intended Audience :: Developers
Classifier: Programming Language :: Python :: 3.10
Classifier: Operating System :: OS Independent
